pyads/__init__.py
pyads/ads.py
pyads/connection.py
pyads/constants.py
pyads/errorcodes.py
pyads/errorcodes_nc.py
pyads/filetimes.py
pyads/pyads_ex.py
pyads/structs.py
pyads/symbol.py
pyads/utils.py
pyads/testserver/__init__.py
pyads/testserver/__main__.py
pyads/testserver/advanced_handler.py
pyads/testserver/basic_handler.py
pyads/testserver/handler.py
pyads/testserver/testserver.py
pyads-3.5.2.dist-info/licenses/LICENSE
pyads-3.5.2.dist-info/METADATA
pyads-3.5.2.dist-info/WHEEL
pyads-3.5.2.dist-info/top_level.txt
pyads-3.5.2.dist-info/RECORD
